{"Type": "AWS::IAM::ManagedPolicy", "Arn": "arn:aws:iam::aws:policy/aws-service-role/AWSLicenseManagerServiceRolePolicy", "Condition": null, "CreatePolicy": null, "DeletionPolicy": null, "DependsOn": null, "Metadata": null, "UpdatePolicy": null, "UpdateReplacePolicy": null, "Properties": {"Description": null, "Groups": null, "ManagedPolicyName": "AWSLicenseManagerServiceRolePolicy", "Path": null, "PolicyDocument": {"Condition": null, "Statement": [{"Condition": null, "Sid": "S3BucketPermissions1", "Effect": "Allow", "Principal": null, "NotPrincipal": null, "Action": ["s3:GetBucketLocation", "s3:ListBucket"], "NotAction": null, "Resource": ["arn:aws:s3:::aws-license-manager-service-*"], "NotResource": null}, {"Condition": null, "Sid": "S3BucketPermissions2", "Effect": "Allow", "Principal": null, "NotPrincipal": null, "Action": ["s3:ListAllMyBuckets"], "NotAction": null, "Resource": ["*"], "NotResource": null}, {"Condition": null, "Sid": "S3ObjectPermissions", "Effect": "Allow", "Principal": null, "NotPrincipal": null, "Action": ["s3:PutObject"], "NotAction": null, "Resource": ["arn:aws:s3:::aws-license-manager-service-*"], "NotResource": null}, {"Condition": null, "Sid": "SNSAccountPermissions", "Effect": "Allow", "Principal": null, "NotPrincipal": null, "Action": ["sns:Publish"], "NotAction": null, "Resource": ["arn:aws:sns:*:*:aws-license-manager-service-*"], "NotResource": null}, {"Condition": null, "Sid": "SNSTopicPermissions", "Effect": "Allow", "Principal": null, "NotPrincipal": null, "Action": ["sns:ListTopics"], "NotAction": null, "Resource": ["*"], "NotResource": null}, {"Condition": null, "Sid": "EC2Permissions", "Effect": "Allow", "Principal": null, "NotPrincipal": null, "Action": ["ec2:DescribeInstances", "ec2:DescribeImages", "ec2:DescribeHosts"], "NotAction": null, "Resource": ["*"], "NotResource": null}, {"Condition": null, "Sid": "SSMPermissions", "Effect": "Allow", "Principal": null, "NotPrincipal": null, "Action": ["ssm:ListInventoryEntries", "ssm:GetInventory", "ssm:CreateAssociation"], "NotAction": null, "Resource": ["*"], "NotResource": null}, {"Condition": null, "Sid": "OrganizationPermissions", "Effect": "Allow", "Principal": null, "NotPrincipal": null, "Action": ["organizations:ListAWSServiceAccessForOrganization", "organizations:DescribeOrganization"], "NotAction": null, "Resource": ["*"], "NotResource": null}, {"Condition": null, "Sid": "LicenseManagerPermissions", "Effect": "Allow", "Principal": null, "NotPrincipal": null, "Action": ["license-manager:GetServiceSettings", "license-manager:GetLicenseConfiguration", "license-manager:UpdateLicenseSpecificationsForResource", "license-manager:ListUsageForLicenseConfiguration"], "NotAction": null, "Resource": ["*"], "NotResource": null}], "Version": "2012-10-17"}, "Roles": null, "Users": null}}