{"Type": "AWS::IAM::ManagedPolicy", "Arn": "arn:aws:iam::aws:policy/AmazonFSxConsoleFullAccess", "Condition": null, "CreatePolicy": null, "DeletionPolicy": null, "DependsOn": null, "Metadata": null, "UpdatePolicy": null, "UpdateReplacePolicy": null, "Properties": {"Description": null, "Groups": null, "ManagedPolicyName": "AmazonFSxConsoleFullAccess", "Path": null, "PolicyDocument": {"Condition": null, "Statement": [{"Condition": null, "Sid": null, "Effect": "Allow", "Principal": null, "NotPrincipal": null, "Action": ["cloudwatch:DescribeAlarms", "ds:DescribeDirectories", "ec2:DescribeNetworkInterfaceAttribute", "ec2:DescribeSecurityGroups", "ec2:DescribeSubnets", "ec2:DescribeVpcs", "fsx:*", "kms:ListAliases", "s3:ListBucket"], "NotAction": null, "Resource": "*", "NotResource": null}, {"Condition": {"StringLike": {"iam:AWSServiceName": ["fsx.amazonaws.com"]}}, "Sid": null, "Effect": "Allow", "Principal": null, "NotPrincipal": null, "Action": "iam:CreateServiceLinkedRole", "NotAction": null, "Resource": "*", "NotResource": null}, {"Condition": {"StringLike": {"iam:AWSServiceName": ["s3.data-source.lustre.fsx.amazonaws.com"]}}, "Sid": null, "Effect": "Allow", "Principal": null, "NotPrincipal": null, "Action": "iam:CreateServiceLinkedRole", "NotAction": null, "Resource": "*", "NotResource": null}], "Version": "2012-10-17"}, "Roles": null, "Users": null}}